{
  "targets": [
    "depthMain",
    "bloomColor",
    "blurSwap",
    "final"
  ],
  "passes": [
    {
      "name": "lodestone:bloom_mask",
      "intarget": "minecraft:main",
      "outtarget": "bloomColor"
    },
    {
      "name": "lodestone:gaussian",
      "intarget": "bloomColor",
      "outtarget": "blurSwap",
      "uniforms": [
        {
          "name": "Direction",
          "values": [0.0]
        }
      ]
    },
    {
      "name": "lodestone:gaussian",
      "intarget": "blurSwap",
      "outtarget": "bloomColor",
      "uniforms": [
        {
          "name": "Direction",
          "values": [1.0]
        }
      ]
    },
    {
      "name": "lodestone:gaussian",
      "intarget": "bloomColor",
      "outtarget": "blurSwap",
      "uniforms": [
        {
          "name": "Direction",
          "values": [0.0]
        }
      ]
    },
    {
      "name": "lodestone:gaussian",
      "intarget": "blurSwap",
      "outtarget": "bloomColor",
      "uniforms": [
        {
          "name": "Direction",
          "values": [1.0]
        }
      ]
    },
    {
      "name": "lodestone:gaussian",
      "intarget": "bloomColor",
      "outtarget": "blurSwap",
      "uniforms": [
        {
          "name": "Direction",
          "values": [0.0]
        }
      ]
    },
    {
      "name": "lodestone:gaussian",
      "intarget": "blurSwap",
      "outtarget": "bloomColor",
      "uniforms": [
        {
          "name": "Direction",
          "values": [1.0]
        }
      ]
    },
    {
      "name": "lodestone:gaussian",
      "intarget": "bloomColor",
      "outtarget": "blurSwap",
      "uniforms": [
        {
          "name": "Direction",
          "values": [0.0]
        }
      ]
    },
    {
      "name": "lodestone:gaussian",
      "intarget": "blurSwap",
      "outtarget": "bloomColor",
      "uniforms": [
        {
          "name": "Direction",
          "values": [1.0]
        }
      ]
    },
    {
      "name": "lodestone:gaussian",
      "intarget": "bloomColor",
      "outtarget": "blurSwap",
      "uniforms": [
        {
          "name": "Direction",
          "values": [0.0]
        }
      ]
    },
    {
      "name": "lodestone:gaussian",
      "intarget": "blurSwap",
      "outtarget": "bloomColor",
      "uniforms": [
        {
          "name": "Direction",
          "values": [1.0]
        }
      ]
    },
    {
      "name": "lodestone:gaussian",
      "intarget": "bloomColor",
      "outtarget": "blurSwap",
      "uniforms": [
        {
          "name": "Direction",
          "values": [0.0]
        }
      ]
    },
    {
      "name": "lodestone:gaussian",
      "intarget": "blurSwap",
      "outtarget": "bloomColor",
      "uniforms": [
        {
          "name": "Direction",
          "values": [1.0]
        }
      ]
    },
    {
      "name": "lodestone:blend",
      "intarget": "minecraft:main",
      "outtarget": "final",
      "auxtargets": [
        {
          "name": "BlendSampler",
          "id": "bloomColor"
        }
      ]
    },
    {
      "name": "blit",
      "intarget": "final",
      "outtarget": "minecraft:main"
    }
  ]
}
